<?xml version="1.0"?>
<!DOCTYPE hibernate-mapping PUBLIC "-//Hibernate/Hibernate Mapping DTD 3.0//EN"
"http://www.hibernate.org/dtd/hibernate-mapping-3.0.dtd">
<!-- Generated 10.07.2012 15:18:27 by Hibernate Tools 3.4.0.CR1 -->
<hibernate-mapping>
    <class name="org.n52.sos.ds.hibernate.CloudjsEntity" 
           table="patches_cloudjs">
        <id name="offering"  type="string">
            <column name="offering_id" />
        </id>
        <property name="cloudjs" type="string" >
            <column name="cloudjs" not-null="true" />
        </property>
        <property name="lx" type="double" >
            <column name="lx" not-null="true" />
        </property>
        <property name="ly" type="double" >
            <column name="ly" not-null="true" />
        </property>
        <property name="lz" type="double" >
            <column name="lz" not-null="true" />
        </property>
        <property name="ux" type="double" >
            <column name="ux" not-null="true" />
        </property>
        <property name="uy" type="double" >
            <column name="uy" not-null="true" />
        </property>
        <property name="uz" type="double" >
            <column name="uz" not-null="true" />
        </property>
        <property name="spacing" type="int" >
            <column name="spacing" not-null="true" />
        </property>
        <property name="scale" type="double" >
            <column name="scale" not-null="true" />
        </property>
        <property name="hierarchystepsize" type="int" >
            <column name="hierarchystepsize" not-null="true" />
        </property>
    </class>
</hibernate-mapping>
